WorkDirectoryGen/__init__.py
WorkDirectoryGen/cli.py
WorkDirectoryGen/core.py
WorkDirectoryGen-0.1.dist-info/LICENSE
WorkDirectoryGen-0.1.dist-info/METADATA
WorkDirectoryGen-0.1.dist-info/WHEEL
WorkDirectoryGen-0.1.dist-info/entry_points.txt
WorkDirectoryGen-0.1.dist-info/top_level.txt
WorkDirectoryGen-0.1.dist-info/RECORD
