Metadata-Version: 2.1
Name: WorkDirectoryGen
Version: 0.1
Classifier: Programming Language :: Python :: 3
Classifier: License :: OSI Approved :: MIT License
Classifier: Operating System :: OS Independent
Requires-Python: >=3.6
License-File: LICENSE
Requires-Dist: pytesseract
Requires-Dist: Pillow
Requires-Dist: PyPDF2
